simplebot_reversi/__init__.py
simplebot_reversi/orm.py
simplebot_reversi/reversi.py
simplebot_reversi-1.0.0.dist-info/LICENSE
simplebot_reversi-1.0.0.dist-info/METADATA
simplebot_reversi-1.0.0.dist-info/WHEEL
simplebot_reversi-1.0.0.dist-info/entry_points.txt
simplebot_reversi-1.0.0.dist-info/top_level.txt
simplebot_reversi-1.0.0.dist-info/RECORD
